makefile
mnemosyne/__init__.py
mnemosyne/example_plugins/activate_cards_on_rollover.py
mnemosyne/example_plugins/add_menu_item.py
mnemosyne/example_plugins/after_repetition.py
mnemosyne/example_plugins/avg_grade_statistics.py
mnemosyne/example_plugins/azure_tts.py
mnemosyne/example_plugins/backup.py
mnemosyne/example_plugins/configuration.py
mnemosyne/example_plugins/custom_tag.py
mnemosyne/example_plugins/filter.py
mnemosyne/example_plugins/google_cloud_tts.py
mnemosyne/example_plugins/grades_criterion.py
mnemosyne/example_plugins/hide_toolbar.py
mnemosyne/example_plugins/html_statistics.py
mnemosyne/example_plugins/lock_down.py
mnemosyne/example_plugins/new_card_type.py
mnemosyne/example_plugins/new_card_type_widget.py
mnemosyne/example_plugins/pie_chart_statistics.py
mnemosyne/example_plugins/README
mnemosyne/example_plugins/responsive_voice_tts.py
mnemosyne/example_plugins/reverse_arabic.py
mnemosyne/example_plugins/shortcuts.py
mnemosyne/example_scripts/add_card.py
mnemosyne/example_scripts/export_stats.py
mnemosyne/example_scripts/export_to_mp3.py
mnemosyne/example_scripts/export_to_pdf.py
mnemosyne/example_scripts/find_and_replace.py
mnemosyne/example_scripts/import_rosetta_stone.py
mnemosyne/example_scripts/README
mnemosyne/example_scripts/silence.mp3
mnemosyne/libmnemosyne/__init__.py
mnemosyne/libmnemosyne/card.py
mnemosyne/libmnemosyne/card_type.py
mnemosyne/libmnemosyne/card_type_converter.py
mnemosyne/libmnemosyne/card_types/__init__.py
mnemosyne/libmnemosyne/card_types/both_ways.py
mnemosyne/libmnemosyne/card_types/cloze.py
mnemosyne/libmnemosyne/card_types/front_to_back.py
mnemosyne/libmnemosyne/card_types/M_sided.py
mnemosyne/libmnemosyne/card_types/map.py
mnemosyne/libmnemosyne/card_types/sentence.py
mnemosyne/libmnemosyne/card_types/vocabulary.py
mnemosyne/libmnemosyne/component.py
mnemosyne/libmnemosyne/component_manager.py
mnemosyne/libmnemosyne/configuration.py
mnemosyne/libmnemosyne/controller.py
mnemosyne/libmnemosyne/controllers/__init__.py
mnemosyne_proj-2.11.0.2.dist-info/entry_points.txt
mnemosyne_proj-2.11.0.2.dist-info/LICENSE
mnemosyne_proj-2.11.0.2.dist-info/METADATA
mnemosyne_proj-2.11.0.2.dist-info/WHEEL
mnemosyne_proj-2.11.0.2.dist-info/RECORD
