Metadata-Version: 2.1
Name: mnemosyne-proj
Version: 2.11.0.2
Summary: a free, open-source, spaced-repetition flashcard program that helps you learn as efficiently as possible.
Author: Peter Bienstman
Author-email: Peter.Bienstman@gmail.com
Requires-Python: >=3.10,<4.0
Classifier: Programming Language :: Python :: 3
Classifier: Programming Language :: Python :: 3.10
Classifier: Programming Language :: Python :: 3.11
Classifier: Programming Language :: Python :: 3.12
Classifier: Programming Language :: Python :: 3.13
Requires-Dist: argon2-cffi (>=21.3.0,<22.0.0)
Requires-Dist: cheroot (>=10.0.0,<11.0.0)
Requires-Dist: cherrypy (>=18.8.0,<19.0.0)
Requires-Dist: decorator (>=5.1.1,<6.0.0)
Requires-Dist: google-trans-new (>=1.1.9,<2.0.0)
Requires-Dist: gtts (>=2.3.2,<3.0.0)
Requires-Dist: legacy-cgi (>=2.6,<3.0)
Requires-Dist: matplotlib (>=3.7.2,<4.0.0)
Requires-Dist: pyqt6 (>=6.5.1,<7.0.0)
Requires-Dist: pyqt6-webengine (>=6.5.0,<7.0.0)
Requires-Dist: pytest (>=7.4.0,<8.0.0)
Requires-Dist: pytest-timeout (>=2.1.0,<3.0.0)
Requires-Dist: sphinx (>=7.0.1,<8.0.0)
Requires-Dist: webob (>=1.8.7,<2.0.0)
